mkdocs_tree
