Metadata-Version: 1.0
Name: mkdocs-tree
Version: 1.0.1
Summary: Tree extension for the mkdocs documentation system.
Home-page: https://github.com/erichulser/mkdocs_autodoc
Author: Eric Hulser
Author-email: eric.hulser@projexsoftware.com
License: LGPL
Platform: UNKNOWN
